llama3tokenizers/__init__.py
llama3tokenizers/tokenizer.json
llama3tokenizers/tokenizer.model
venv/test.py
llama3tokenizers-0.0.2.dist-info/LICENSE
llama3tokenizers-0.0.2.dist-info/METADATA
llama3tokenizers-0.0.2.dist-info/WHEEL
llama3tokenizers-0.0.2.dist-info/top_level.txt
llama3tokenizers-0.0.2.dist-info/RECORD
