Metadata-Version: 2.1
Name: llama3tokenizers
Version: 0.0.2
Summary: a place downloading llama3tokenizers
License-File: LICENSE
